MANIFEST.in
README.md
setup.cfg
setup.py
src/irgsctool/__init__.py
src/irgsctool/_extinction_correction.py
src/irgsctool/_fitting.py
src/irgsctool/_get_data.py
src/irgsctool/_read_data.py
src/irgsctool/_sam.py
src/irgsctool/_sgc.py
src/irgsctool/_validate.py
src/irgsctool/old_init.py
src/irgsctool.egg-info/PKG-INFO
src/irgsctool.egg-info/SOURCES.txt
src/irgsctool.egg-info/dependency_links.txt
src/irgsctool.egg-info/requires.txt
src/irgsctool.egg-info/top_level.txt
src/irgsctool/data/interpolated_kurucz.txt
src/irgsctool/data/interpolated_phoenix.txt