Metadata-Version: 2.1
Name: irgsctool
Version: 1.1.5
Summary: Python tool to generate a catalog of NIR guide stars for the AO observations of the Thirty Meter Telescope.
Home-page: UNKNOWN
Author: Sarang Shah
Author-email: sshah1502@gmail.com
License: BSD 2-clause
Platform: UNKNOWN
Classifier: Development Status :: 4 - Beta
Classifier: Intended Audience :: Science/Research
Classifier: License :: OSI Approved :: BSD License
Classifier: Operating System :: OS Independent
Classifier: Programming Language :: Python :: 3.6
Classifier: Programming Language :: Python :: 3.9
